{
  "test_id": "T02_tiebreak_deadline",
  "passed": true,
  "errors": [],
  "result": {
    "selectedJob": "CP-202",
    "selectionReason": "Highest priority score after tie-break by earlier deadline",
    "candidates": [
      {
        "jobId": "CP-202",
        "priorityScore": 32,
        "assignedPriority": "P0",
        "severity": 4,
        "blockingBreadth": 0,
        "deadlineProximity": 5,
        "businessImpact": 4,
        "executionReadiness": 4,
        "executionEffort": 2,
        "estimatedTokens": 15000,
        "selected": true,
        "selectedReason": "Highest priority score after tie-break by earlier deadline",
        "tieBreakReason": "earlier deadline",
        "eligible": true
      },
      {
        "jobId": "CP-203",
        "priorityScore": 32,
        "assignedPriority": "P0",
        "severity": 4,
        "blockingBreadth": 0,
        "deadlineProximity": 5,
        "businessImpact": 4,
        "executionReadiness": 4,
        "executionEffort": 2,
        "estimatedTokens": 15000,
        "selected": false,
        "selectedReason": "Lost tie-break to CP-202 by earlier deadline",
        "tieBreakReason": "earlier deadline",
        "eligible": true
      },
      {
        "jobId": "CP-204",
        "priorityScore": 12,
        "assignedPriority": "P2",
        "severity": 1,
        "blockingBreadth": 0,
        "deadlineProximity": 3,
        "businessImpact": 0,
        "executionReadiness": 4,
        "executionEffort": 1,
        "estimatedTokens": 7000,
        "selected": false,
        "selectedReason": "Lower priority score than CP-202",
        "eligible": true
      }
    ],
    "safetyEvaluation": {
      "blocked": false,
      "blockedBy": [],
      "requiresOperatorApproval": false
    },
    "approvalDecision": {
      "approved": true,
      "mode": "jobs",
      "reason": "jobs window active (5 remaining)"
    },
    "outcome": "dispatch",
    "riskyHeld": [],
    "tieBreakReason": "earlier deadline",
    "selectedPriority": "P0",
    "selectedScore": 32
  },
  "summary": "Next job selected: CP-202\nPriority: P0\nScore: 32\nReason: Highest priority score after tie-break by earlier deadline\nTie-break: earlier deadline\nEstimated tokens: 15000\nSafety status: eligible\nApproval window: jobs / jobs window active (5 remaining)\nAction: dispatching now",
  "evidence": {
    "after_state": {
      "version": 1,
      "mode": "jobs",
      "jobsRemaining": 4,
      "maxJobs": 5,
      "windowStartedAt": "2026-03-25T09:00:00Z",
      "windowExpiresAt": null,
      "followNewJobs": false,
      "allowDestructive": false,
      "allowProdChanges": false,
      "maxTokensPerJob": 120000,
      "maxTokensPerWindow": 400000,
      "windowTokensUsed": 10950,
      "windowCompletedJobs": [
        "CP-202"
      ],
      "sessionCompletedJobs": [
        "CP-202"
      ],
      "lastDispatchedJobId": "CP-202",
      "lastUpdatedAt": "2026-03-25T18:35:02.198578+00:00"
    },
    "execution_metrics": {
      "testId": "T02_tiebreak_deadline",
      "jobId": "CP-202",
      "runtimeMs": 908,
      "actualTokensUsed": 10950,
      "retryCount": 0,
      "dispatchAttempts": 1,
      "estimatedTokens": 15000,
      "auditRuntimeMs": 0
    },
    "quarantine": {
      "jobId": "CP-202",
      "quarantined": false,
      "reason": null,
      "failedAttempts": 0
    },
    "blocked_downstream": {
      "testId": "T02_tiebreak_deadline",
      "rootFailedJobId": null,
      "blockedJobs": [],
      "count": 0
    },
    "window_accounting": {
      "testId": "T02_tiebreak_deadline",
      "jobId": "CP-202",
      "mode": "jobs",
      "jobsRemainingBefore": 5,
      "jobsRemainingAfter": 4,
      "windowTokensBefore": 0,
      "windowTokensAfter": 10950,
      "actualTokensUsed": 10950
    },
    "slot_consumption": {
      "testId": "T02_tiebreak_deadline",
      "jobId": "CP-202",
      "jobsRemainingBefore": 5,
      "jobsRemainingAfter": 4,
      "slotConsumed": true,
      "evidence": "dispatch entered execution"
    },
    "safety_report": {
      "testId": "T02_tiebreak_deadline",
      "jobId": "CP-202",
      "eligible": true,
      "blocked": false,
      "blockedBy": [],
      "approvalReason": "jobs window active (5 remaining)"
    },
    "validator_output": {
      "testId": "T02_tiebreak_deadline",
      "passed": true,
      "selectedJob": "CP-202",
      "selectedPriority": "P0",
      "selectedScore": 32,
      "errors": []
    }
  }
}