{
  "test_id": "T02_tiebreak_deadline",
  "passed": true,
  "errors": [],
  "result": {
    "selectedJob": "CP-202",
    "selectionReason": "Selected CP-202 (score: 25, priority: P0)",
    "candidates": [
      {
        "jobId": "CP-202",
        "score": 25,
        "priority": "P0",
        "eligible": true
      },
      {
        "jobId": "CP-203",
        "score": 23,
        "priority": "P0",
        "eligible": true
      },
      {
        "jobId": "CP-204",
        "score": 16,
        "priority": "P1",
        "eligible": true
      }
    ],
    "safetyEvaluation": {
      "blocked": false,
      "blockedBy": [],
      "requiresOperatorApproval": false
    },
    "approvalDecision": {
      "approved": true,
      "mode": "jobs",
      "reason": "jobs window active (5 remaining)"
    },
    "outcome": "dispatch",
    "riskyHeld": []
  },
  "summary": "Selected: CP-202\nOutcome: dispatch\nPriority: P0 (score: 25)\nTitle: Review release checklist before handoff\nApproval: jobs window active (5 remaining)"
}